repl_cli/__init__.py
repl_cli/__main__.py
repl_cli/main.py
repl_cli-1.2.7.dist-info/entry_points.txt
repl_cli-1.2.7.dist-info/LICENSE
repl_cli-1.2.7.dist-info/WHEEL
repl_cli-1.2.7.dist-info/METADATA
repl_cli-1.2.7.dist-info/RECORD
