Metadata-Version: 2.1
Name: repl-cli
Version: 1.2.7
Summary: 
Author: SnowCoder
Author-email: donot@email.me
Requires-Python: >=3.8,<4.0
Classifier: Programming Language :: Python :: 3
Classifier: Programming Language :: Python :: 3.10
Classifier: Programming Language :: Python :: 3.8
Classifier: Programming Language :: Python :: 3.9
Requires-Dist: datauri (>=1.0.0,<2.0.0)
Requires-Dist: replit[all] (>=3.1.0,<4.0.0)
Requires-Dist: requests[all] (>=2.25.1,<3.0.0)
Requires-Dist: snow-pyrepl[all] (>=0.50,<0.51)
Requires-Dist: typer[all] (>=0.3.2,<0.4.0)
Requires-Dist: watchdog[all] (>=2.1.5,<3.0.0)
